{
  "hash": "f0afd008",
  "configHash": "511f9caf",
  "lockfileHash": "62fab7d5",
  "browserHash": "bc24366c",
  "optimized": {
    "@vue/devtools-api": {
      "src": "../../../../node_modules/@vue/devtools-api/dist/index.js",
      "file": "@vue_devtools-api.js",
      "fileHash": "9dc64319",
      "needsInterop": false
    },
    "@vuepress/shared": {
      "src": "../../../../node_modules/@vuepress/shared/dist/index.js",
      "file": "@vuepress_shared.js",
      "fileHash": "3b1968a7",
      "needsInterop": false
    },
    "vue": {
      "src": "../../../../node_modules/vue/dist/vue.runtime.esm-bundler.js",
      "file": "vue.js",
      "fileHash": "b9a41e52",
      "needsInterop": false
    },
    "vue-router": {
      "src": "../../../../node_modules/vue-router/dist/vue-router.esm-bundler.js",
      "file": "vue-router.js",
      "fileHash": "10c38540",
      "needsInterop": false
    }
  },
  "chunks": {
    "chunk-LW4I4DCF": {
      "file": "chunk-LW4I4DCF.js"
    }
  }
}